Metadata-Version: 2.1
Name: rnalib
Version: 0.0.4
Summary: A python-based transcriptomics library
Home-page: https://github.com/popitsch/rnalib
Author: Niko Popitsch
Author-email: niko.popitsch@univie.ac.at
License: Apache-2.0
Project-URL: Changelog, https://github.com/popitsch/rnalib/blob/main/CHANGELOG.md
Project-URL: Issues, https://github.com/popitsch/rnalib/issues
Project-URL: Source Code, https://github.com/popitsch/rnalib
Classifier: Development Status :: 3 - Alpha
Classifier: Intended Audience :: Developers
Classifier: Topic :: Software Development :: Libraries :: Python Modules
Classifier: License :: OSI Approved :: Apache Software License
Classifier: Programming Language :: Python :: 3
Requires-Python: >=3.10
License-File: LICENSE
Requires-Dist: setuptools
Requires-Dist: bioframe
Requires-Dist: biotite
Requires-Dist: dill
Requires-Dist: h5py
Requires-Dist: intervaltree
Requires-Dist: ipython
Requires-Dist: matplotlib
Requires-Dist: seaborn
Requires-Dist: more_itertools
Requires-Dist: mygene
Requires-Dist: numpy
Requires-Dist: pandas
Requires-Dist: pybedtools
Requires-Dist: pyranges
Requires-Dist: pysam
Requires-Dist: pytest
Requires-Dist: sortedcontainers
Requires-Dist: tqdm
Requires-Dist: arrow
Requires-Dist: pyarrow
Requires-Dist: s3fs
Requires-Dist: HTSeq
Requires-Dist: pyBigWig
Requires-Dist: termcolor
